{
	"$schema": "http://schema.management.azure.com/schemas/2015-01-01/deploymentTemplate.json#",
	"contentVersion": "1.0.0.0",
	"parameters": {
		"factoryName": {
			"type": "string",
			"metadata": "Data Factory name",
			"defaultValue": "ugodffactory"
		}
	},
	"variables": {
		"factoryId": "[concat('Microsoft.DataFactory/factories/', parameters('factoryName'))]"
	},
	"resources": [
		{
			"name": "[concat(parameters('factoryName'), '/DeltaCopyFromBlobPipeline')]",
			"type": "Microsoft.DataFactory/factories/pipelines",
			"apiVersion": "2018-06-01",
			"properties": {
				"activities": [
					{
						"name": "CopyFiles",
						"type": "Copy",
						"dependsOn": [],
						"policy": {
							"timeout": "7.00:00:00",
							"retry": 0,
							"retryIntervalInSeconds": 30,
							"secureOutput": false,
							"secureInput": false
						},
						"userProperties": [
							{
								"name": "Source",
								"value": "source//"
							},
							{
								"name": "Destination",
								"value": "destination//"
							}
						],
						"typeProperties": {
							"source": {
								"type": "BinarySource",
								"storeSettings": {
									"type": "AzureBlobStorageReadSettings",
									"recursive": true,
									"modifiedDatetimeStart": {
										"value": "@pipeline().parameters.windowStart",
										"type": "Expression"
									},
									"modifiedDatetimeEnd": {
										"value": "@pipeline().parameters.windowEnd",
										"type": "Expression"
									},
									"wildcardFileName": "*"
								},
								"formatSettings": {
									"type": "BinaryReadSettings"
								}
							},
							"sink": {
								"type": "BinarySink",
								"storeSettings": {
									"type": "AzureBlobStorageWriteSettings"
								}
							},
							"enableStaging": false,
							"enableSkipIncompatibleRow": false,
							"skipErrorFile": {
								"fileMissing": true
							},
							"validateDataConsistency": false
						},
						"inputs": [
							{
								"referenceName": "SourceDataset_7kk",
								"type": "DatasetReference"
							}
						],
						"outputs": [
							{
								"referenceName": "DestinationDataset_7kk",
								"type": "DatasetReference"
							}
						]
					}
				],
				"parameters": {
					"windowStart": {
						"type": "String"
					},
					"windowEnd": {
						"type": "String"
					}
				},
				"annotations": [],
				"lastPublishTime": "2020-10-21T14:57:42Z"
			},
			"dependsOn": []
		}
	]
}